edx_proctoring/__init__.py
edx_proctoring/admin.py
edx_proctoring/api.py
edx_proctoring/apps.py
edx_proctoring/callbacks.py
edx_proctoring/constants.py
edx_proctoring/decorators.py
edx_proctoring/exceptions.py
edx_proctoring/handlers.py
edx_proctoring/instructor_dashboard_exam_urls.py
edx_proctoring/models.py
edx_proctoring/rules.py
edx_proctoring/runtime.py
edx_proctoring/serializers.py
edx_proctoring/services.py
edx_proctoring/signals.py
edx_proctoring/statuses.py
edx_proctoring/urls.py
edx_proctoring/utils.py
edx_proctoring/views.py
edx_proctoring/backends/LICENSE.txt
edx_proctoring/backends/README.txt
edx_proctoring/backends/__init__.py
edx_proctoring/backends/backend.py
edx_proctoring/backends/mock.py
edx_proctoring/backends/null.py
edx_proctoring/backends/rest.py
edx_proctoring/backends/software_secure.py
edx_proctoring/backends/tests/__init__.py
edx_proctoring/backends/tests/test_backend.py
edx_proctoring/backends/tests/test_rest.py
edx_proctoring/backends/tests/test_review_payload.py
edx_proctoring/backends/tests/test_software_secure.py
edx_proctoring/locale/config.yaml
edx_proctoring/locale/ar/LC_MESSAGES/django.mo
edx_proctoring/locale/ar/LC_MESSAGES/django.po
edx_proctoring/locale/ar/LC_MESSAGES/djangojs.mo
edx_proctoring/locale/ar/LC_MESSAGES/djangojs.po
edx_proctoring/locale/ca/LC_MESSAGES/django.mo
edx_proctoring/locale/ca/LC_MESSAGES/django.po
edx_proctoring/locale/ca/LC_MESSAGES/djangojs.mo
edx_proctoring/locale/ca/LC_MESSAGES/djangojs.po
edx_proctoring/locale/cs/LC_MESSAGES/django.mo
edx_proctoring/locale/cs/LC_MESSAGES/django.po
edx_proctoring/locale/cs/LC_MESSAGES/djangojs.mo
edx_proctoring/locale/cs/LC_MESSAGES/djangojs.po
edx_proctoring/locale/de_DE/LC_MESSAGES/django.mo
edx_proctoring/locale/de_DE/LC_MESSAGES/django.po
edx_proctoring/locale/de_DE/LC_MESSAGES/djangojs.mo
edx_proctoring/locale/de_DE/LC_MESSAGES/djangojs.po
edx_proctoring/locale/el/LC_MESSAGES/django.mo
edx_proctoring/locale/el/LC_MESSAGES/django.po
edx_proctoring-5.2.0.dist-info/LICENSE.txt
edx_proctoring-5.2.0.dist-info/METADATA
edx_proctoring-5.2.0.dist-info/WHEEL
edx_proctoring-5.2.0.dist-info/entry_points.txt
edx_proctoring-5.2.0.dist-info/top_level.txt
edx_proctoring-5.2.0.dist-info/RECORD
