Metadata-Version: 2.1
Name: edx-proctoring
Version: 5.2.0
Summary: Proctoring subsystem for Open edX
Home-page: https://github.com/openedx/edx-proctoring
Author: edX
Author-email: oscm@edx.org
License: AGPL 3.0
Keywords: Django edx
Classifier: Development Status :: 4 - Beta
Classifier: Framework :: Django
Classifier: Framework :: Django :: 4.2
Classifier: Framework :: Django :: 5.2
Classifier: Intended Audience :: Developers
Classifier: License :: OSI Approved :: GNU Affero General Public License v3 or later (AGPLv3+)
Classifier: Natural Language :: English
Classifier: Programming Language :: Python :: 3.8
Classifier: Programming Language :: Python :: 3.11
Classifier: Programming Language :: Python :: 3.12
License-File: LICENSE.txt
Requires-Dist: jsonfield
Requires-Dist: django-waffle
Requires-Dist: django-crum
Requires-Dist: edx-drf-extensions
Requires-Dist: pycryptodomex>=3.4.7
Requires-Dist: django-model-utils
Requires-Dist: edx-when>=0.1.3
Requires-Dist: python-dateutil>=2.1
Requires-Dist: edx-opaque-keys>=0.4
Requires-Dist: pytz>=2018
Requires-Dist: event-tracking>=0.2.5
Requires-Dist: django-webpack-loader>=0.6.0
Requires-Dist: django-ipware>=1.1.0
Requires-Dist: edx-rest-api-client>=1.9.2
Requires-Dist: pyjwt[crypto]>=2.1.0
Requires-Dist: django-simple-history
Requires-Dist: Django>=2.2
Requires-Dist: djangorestframework
Requires-Dist: rules
